pytest_helpers/asyncs.py
pytest_helpers/deployment_test.py
pytest_helpers-0.1.0.dist-info/LICENSE
pytest_helpers-0.1.0.dist-info/METADATA
pytest_helpers-0.1.0.dist-info/WHEEL
pytest_helpers-0.1.0.dist-info/entry_points.txt
pytest_helpers-0.1.0.dist-info/top_level.txt
pytest_helpers-0.1.0.dist-info/RECORD
